rl_inventory_api/__init__.py
rl_inventory_api/inventory.py
rl_inventory_api/item.py
rl_inventory_api/constants/__init__.py
rl_inventory_api/constants/certifies.py
rl_inventory_api/constants/colors.py
rl_inventory_api/constants/rarities.py
rl_inventory_api/constants/series.py
rl_inventory_api/constants/tradeable.py
rl_inventory_api/constants/types.py
rl_inventory_api-0.0.2.dist-info/LICENSE.txt
rl_inventory_api-0.0.2.dist-info/METADATA
rl_inventory_api-0.0.2.dist-info/WHEEL
rl_inventory_api-0.0.2.dist-info/top_level.txt
rl_inventory_api-0.0.2.dist-info/RECORD
