Metadata-Version: 2.1
Name: rl-inventory-api
Version: 0.0.2
Summary: Easy way to interact with your Bakkesmod inventory.
Home-page: https://github.com/TheVicio/Rl-Inventory-Api
Author: TheVicio
Author-email: thevicio27@gmail.com
License: UNKNOWN
Project-URL: Bug Tracker, https://github.com/TheVicio/Rl-Inventory-Api/issues
Platform: UNKNOWN
Classifier: Programming Language :: Python :: 3
Classifier: License :: OSI Approved :: MIT License
Classifier: Operating System :: OS Independent
Requires-Python: >=3.6
License-File: LICENSE.txt
